pydockerfile/__init__.py
pydockerfile/_version.py
pydockerfile/dockerfile.py
pydockerfile/parser.py
pydockerfile-0.0.3.dist-info/top_level.txt
pydockerfile-0.0.3.dist-info/METADATA
pydockerfile-0.0.3.dist-info/DESCRIPTION.rst
pydockerfile-0.0.3.dist-info/metadata.json
pydockerfile-0.0.3.dist-info/WHEEL
pydockerfile-0.0.3.dist-info/RECORD
